boto3r/__init__.py
boto3r/s3.py
boto3r-0.0.4.dist-info/LICENSE
boto3r-0.0.4.dist-info/METADATA
boto3r-0.0.4.dist-info/WHEEL
boto3r-0.0.4.dist-info/top_level.txt
boto3r-0.0.4.dist-info/RECORD
