Metadata-Version: 2.1
Name: boto3r
Version: 0.0.4
Summary: Library that encapsulate Boto3 in option.Result
Home-page: https://github.com/gilcu2/boto3-result
Author: Reynaldo Gil
Author-email: gilcu2@gmail.com
License: UNKNOWN
Keywords: boto3,option,functional programming
Platform: UNKNOWN
Classifier: Programming Language :: Python :: 3
Classifier: License :: OSI Approved :: MIT License
Classifier: Operating System :: OS Independent
Requires-Python: >=3.7
License-File: LICENSE
Requires-Dist: boto3
Requires-Dist: option
